diretree/__init__.py
diretree/diretree.py
diretree-0.0.1.dist-info/LICENSE
diretree-0.0.1.dist-info/METADATA
diretree-0.0.1.dist-info/WHEEL
diretree-0.0.1.dist-info/top_level.txt
diretree-0.0.1.dist-info/RECORD
